test_libb/__init__.py
test_libb/main.py
test_libb-0.0.1.dist-info/METADATA
test_libb-0.0.1.dist-info/WHEEL
test_libb-0.0.1.dist-info/top_level.txt
test_libb-0.0.1.dist-info/RECORD
